pymysqlhelper/__init__.py
pymysqlhelper/database.py
pymysqlhelper-1.10.1.dist-info/licenses/LICENSE
pymysqlhelper-1.10.1.dist-info/METADATA
pymysqlhelper-1.10.1.dist-info/WHEEL
pymysqlhelper-1.10.1.dist-info/entry_points.txt
pymysqlhelper-1.10.1.dist-info/top_level.txt
pymysqlhelper-1.10.1.dist-info/RECORD
