Metadata-Version: 2.4
Name: pymysqlhelper
Version: 1.10.1
Summary: A simple MySQL database helper for easy interactions
Author: DEAMJAVA
Author-email: deamminecraft3@gmail.com
Requires-Python: >=3.6
License-File: LICENSE
Requires-Dist: pymysql
Requires-Dist: sqlalchemy
Dynamic: author
Dynamic: author-email
Dynamic: description
Dynamic: description-content-type
Dynamic: license-file
Dynamic: requires-dist
Dynamic: requires-python
Dynamic: summary
